README.md
setup.py
mongo_watch.egg-info/PKG-INFO
mongo_watch.egg-info/SOURCES.txt
mongo_watch.egg-info/dependency_links.txt
mongo_watch.egg-info/entry_points.txt
mongo_watch.egg-info/not-zip-safe
mongo_watch.egg-info/top_level.txt
mwatch/__init__.py
mwatch/live_query.py
mwatch/main.py
mwatch/oplog.py
mwatch/test.py