Metadata-Version: 1.1
Name: mongo-watch
Version: 0.0.dev11
Summary: Watch the MongoDB oplog
Home-page: UNKNOWN
Author: Rick Copeland
Author-email: rick@arborian.com
License: UNKNOWN
Platform: UNKNOWN
Classifier: Programming Language :: Python
